{"data":[{"moonrise_ts":1611559976,"wind_cdir":"SSW","rh":83,"pres":1007.12,"high_temp":28.9,"sunset_ts":1611573763,"ozone":237.321,"moon_phase":0.910224,"wind_gust_spd":2.20703,"snow_depth":0,"clouds":86,"ts":1611504060,"sunrise_ts":1611530515,"app_min_temp":24.2,"wind_spd":1.21832,"pop":85,"wind_cdir_full":"south-southwest","slp":1009.12,"moon_phase_lunation":0.4,"valid_date":"2021-01-25","app_max_temp":33.5,"vis":16.169,"dewpt":22.9,"snow":0,"uv":3.17524,"weather":{"icon":"r03d","code":502,"description":"Heavy rain"},"wind_dir":213,"max_dhi":null,"clouds_hi":79,"precip":17,"low_temp":23.1,"max_temp":29.2,"moonset_ts":1611521855,"datetime":"2021-01-25","temp":26.1,"min_temp":23.3,"clouds_mid":0,"clouds_low":11},{"moonrise_ts":1611649358,"wind_cdir":"SSE","rh":83,"pres":1006.33,"high_temp":31.2,"sunset_ts":1611660178,"ozone":240.531,"moon_phase":0.96067,"wind_gust_spd":4.41016,"snow_depth":0,"clouds":76,"ts":1611590460,"sunrise_ts":1611616926,"app_min_temp":23.7,"wind_spd":1.346,"pop":60,"wind_cdir_full":"south-southeast","slp":1008.46,"moon_phase_lunation":0.43,"valid_date":"2021-01-26","app_max_temp":35.4,"vis":23.91,"dewpt":22.8,"snow":0,"uv":5.37555,"weather":{"icon":"c04d","code":804,"description":"Overcast clouds"},"wind_dir":158,"max_dhi":null,"clouds_hi":75,"precip":4.75,"low_temp":22.5,"max_temp":32,"moonset_ts":1611611495,"datetime":"2021-01-26","temp":26.2,"min_temp":22.9,"clouds_mid":0,"clouds_low":1},{"moonrise_ts":1611738920,"wind_cdir":"SE","rh":76,"pres":1006.27,"high_temp":33.2,"sunset_ts":1611746593,"ozone":242.156,"moon_phase":0.991097,"wind_gust_spd":3.60352,"snow_depth":0,"clouds":66,"ts":1611676860,"sunrise_ts":1611703336,"app_min_temp":23.1,"wind_spd":1.47572,"pop":45,"wind_cdir_full":"southeast","slp":1008.35,"moon_phase_lunation":0.47,"valid_date":"2021-01-27","app_max_temp":36.4,"vis":23.9513,"dewpt":21.7,"snow":0,"uv":5.27851,"weather":{"icon":"c03d","code":803,"description":"Broken clouds"},"wind_dir":136,"max_dhi":null,"clouds_hi":65,"precip":2.3125,"low_temp":22.5,"max_temp":33.6,"moonset_ts":1611701184,"datetime":"2021-01-27","temp":26.6,"min_temp":22.4,"clouds_mid":4,"clouds_low":0},{"moonrise_ts":1611828608,"wind_cdir":"SSE","rh":82,"pres":1007.29,"high_temp":31,"sunset_ts":1611833007,"ozone":242.943,"moon_phase":0.998361,"wind_gust_spd":2.89844,"snow_depth":0,"clouds":87,"ts":1611763260,"sunrise_ts":1611789745,"app_min_temp":24.1,"wind_spd":1.0968,"pop":80,"wind_cdir_full":"south-southeast","slp":1009.5,"moon_phase_lunation":0.5,"valid_date":"2021-01-28","app_max_temp":35.1,"vis":21.5534,"dewpt":22.8,"snow":0,"uv":5.83935,"weather":{"icon":"r02d","code":501,"description":"Moderate rain"},"wind_dir":151,"max_dhi":null,"clouds_hi":78,"precip":10.625,"low_temp":22.6,"max_temp":31.7,"moonset_ts":1611790840,"datetime":"2021-01-28","temp":26.4,"min_temp":23.2,"clouds_mid":39,"clouds_low":2},{"moonrise_ts":1611918341,"wind_cdir":"SE","rh":77,"pres":1007.62,"high_temp":32.8,"sunset_ts":1611919420,"ozone":241.203,"moon_phase":0.980523,"wind_gust_spd":4.71094,"snow_depth":0,"clouds":88,"ts":1611849660,"sunrise_ts":1611876153,"app_min_temp":23.2,"wind_spd":1.62359,"pop":50,"wind_cdir_full":"southeast","slp":1010.12,"moon_phase_lunation":0.53,"valid_date":"2021-01-29","app_max_temp":34.4,"vis":23.7707,"dewpt":21.6,"snow":0,"uv":5.85963,"weather":{"icon":"c04d","code":804,"description":"Overcast clouds"},"wind_dir":144,"max_dhi":null,"clouds_hi":76,"precip":3.0625,"low_temp":22.4,"max_temp":32.9,"moonset_ts":1611880400,"datetime":"2021-01-29","temp":26.4,"min_temp":22.3,"clouds_mid":11,"clouds_low":13},{"moonrise_ts":1612008038,"wind_cdir":"SE","rh":78,"pres":1008.15,"high_temp":32.2,"sunset_ts":1612005833,"ozone":241.413,"moon_phase":0.980523,"wind_gust_spd":2.60547,"snow_depth":0,"clouds":86,"ts":1611936060,"sunrise_ts":1611962560,"app_min_temp":23.9,"wind_spd":1.14231,"pop":25,"wind_cdir_full":"southeast","slp":1010.5,"moon_phase_lunation":0.57,"valid_date":"2021-01-30","app_max_temp":33.2,"vis":24.048,"dewpt":21.5,"snow":0,"uv":5.55015,"weather":{"icon":"c04d","code":804,"description":"Overcast clouds"},"wind_dir":145,"max_dhi":null,"clouds_hi":60,"precip":0.9375,"low_temp":22.8,"max_temp":32,"moonset_ts":1611966800,"datetime":"2021-01-30","temp":25.7,"min_temp":22.9,"clouds_mid":22,"clouds_low":36},{"moonrise_ts":1612097646,"wind_cdir":"SE","rh":76,"pres":1007.62,"high_temp":31.7,"sunset_ts":1612092244,"ozone":240.344,"moon_phase":0.937258,"wind_gust_spd":2.09961,"snow_depth":0,"clouds":98,"ts":1612022460,"sunrise_ts":1612048967,"app_min_temp":23.4,"wind_spd":0.996595,"pop":45,"wind_cdir_full":"southeast","slp":1009.94,"moon_phase_lunation":0.6,"valid_date":"2021-01-31","app_max_temp":35,"vis":22.016,"dewpt":21.3,"snow":0,"uv":3.21384,"weather":{"icon":"c04d","code":804,"description":"Overcast clouds"},"wind_dir":135,"max_dhi":null,"clouds_hi":91,"precip":2.5,"low_temp":22.9,"max_temp":32.3,"moonset_ts":1612056241,"datetime":"2021-01-31","temp":26.2,"min_temp":22.7,"clouds_mid":0,"clouds_low":20},{"moonrise_ts":1612187154,"wind_cdir":"SSE","rh":80,"pres":1007.94,"high_temp":32.3,"sunset_ts":1612178655,"ozone":241.547,"moon_phase":0.870014,"wind_gust_spd":3,"snow_depth":0,"clouds":67,"ts":1612108860,"sunrise_ts":1612135372,"app_min_temp":23.6,"wind_spd":1.08123,"pop":80,"wind_cdir_full":"south-southeast","slp":1010.12,"moon_phase_lunation":0.64,"valid_date":"2021-02-01","app_max_temp":34.9,"vis":20.975,"dewpt":22.1,"snow":0,"uv":7.9658,"weather":{"icon":"r02d","code":501,"description":"Moderate rain"},"wind_dir":149,"max_dhi":null,"clouds_hi":57,"precip":10.875,"low_temp":22.9,"max_temp":32.7,"moonset_ts":1612145578,"datetime":"2021-02-01","temp":26.1,"min_temp":22.5,"clouds_mid":8,"clouds_low":16},{"moonrise_ts":1612276585,"wind_cdir":"SSE","rh":79,"pres":1008.38,"high_temp":29.1,"sunset_ts":1612265066,"ozone":243.734,"moon_phase":0.781958,"wind_gust_spd":3.62305,"snow_depth":0,"clouds":100,"ts":1612195260,"sunrise_ts":1612221777,"app_min_temp":23.7,"wind_spd":1.0894,"pop":40,"wind_cdir_full":"south-southeast","slp":1010.56,"moon_phase_lunation":0.67,"valid_date":"2021-02-02","app_max_temp":36,"vis":21.897,"dewpt":22.2,"snow":0,"uv":3.2364,"weather":{"icon":"c04d","code":804,"description":"Overcast clouds"},"wind_dir":151,"max_dhi":null,"clouds_hi":100,"precip":2.0625,"low_temp":23.4,"max_temp":32.6,"moonset_ts":1612234855,"datetime":"2021-02-02","temp":26.3,"min_temp":22.7,"clouds_mid":5,"clouds_low":7},{"moonrise_ts":1612365989,"wind_cdir":"WSW","rh":84,"pres":1008.5,"high_temp":30.5,"sunset_ts":1612351475,"ozone":245.891,"moon_phase":0.677752,"wind_gust_spd":2.41211,"snow_depth":0,"clouds":100,"ts":1612281660,"sunrise_ts":1612308181,"app_min_temp":24.2,"wind_spd":0.939495,"pop":85,"wind_cdir_full":"west-southwest","slp":1010.62,"moon_phase_lunation":0.7,"valid_date":"2021-02-03","app_max_temp":33.6,"vis":18.834,"dewpt":23,"snow":0,"uv":3.24635,"weather":{"icon":"r03d","code":502,"description":"Heavy rain"},"wind_dir":245,"max_dhi":null,"clouds_hi":100,"precip":18.5625,"low_temp":22.8,"max_temp":30.3,"moonset_ts":1612324135,"datetime":"2021-02-03","temp":26,"min_temp":23,"clouds_mid":22,"clouds_low":15},{"moonrise_ts":1612369028,"wind_cdir":"WSW","rh":83,"pres":1009,"high_temp":27.5,"sunset_ts":1612437884,"ozone":247,"moon_phase":0.563224,"wind_gust_spd":2.10547,"snow_depth":0,"clouds":100,"ts":1612368060,"sunrise_ts":1612394584,"app_min_temp":25.3,"wind_spd":1.48708,"pop":70,"wind_cdir_full":"west-southwest","slp":1011.25,"moon_phase_lunation":0.74,"valid_date":"2021-02-04","app_max_temp":32.1,"vis":22.152,"dewpt":23.2,"snow":0,"uv":3.25767,"weather":{"icon":"r01d","code":500,"description":"Light rain"},"wind_dir":240,"max_dhi":null,"clouds_hi":100,"precip":7.125,"low_temp":22.9,"max_temp":28.5,"moonset_ts":1612413484,"datetime":"2021-02-04","temp":26.3,"min_temp":23.2,"clouds_mid":60,"clouds_low":40},{"moonrise_ts":1612458562,"wind_cdir":"SSE","rh":88,"pres":1009,"high_temp":29,"sunset_ts":1612524292,"ozone":248.5,"moon_phase":0.444977,"wind_gust_spd":0.907715,"snow_depth":0,"clouds":100,"ts":1612454460,"sunrise_ts":1612480986,"app_min_temp":24.2,"wind_spd":1.06268,"pop":60,"wind_cdir_full":"south-southeast","slp":1011.5,"moon_phase_lunation":0.77,"valid_date":"2021-02-05","app_max_temp":29.6,"vis":24.128,"dewpt":22.8,"snow":0,"uv":3.26931,"weather":{"icon":"c04d","code":804,"description":"Overcast clouds"},"wind_dir":157,"max_dhi":null,"clouds_hi":100,"precip":4.9375,"low_temp":23.5,"max_temp":27.5,"moonset_ts":1612502963,"datetime":"2021-02-05","temp":25.1,"min_temp":23.1,"clouds_mid":91,"clouds_low":21},{"moonrise_ts":1612548238,"wind_cdir":"E","rh":77,"pres":1007.75,"high_temp":33,"sunset_ts":1612610699,"ozone":250.5,"moon_phase":0.329931,"wind_gust_spd":2.30469,"snow_depth":0,"clouds":88,"ts":1612540860,"sunrise_ts":1612567388,"app_min_temp":23.8,"wind_spd":1.13917,"pop":35,"wind_cdir_full":"east","slp":1010.25,"moon_phase_lunation":0.8,"valid_date":"2021-02-06","app_max_temp":34.6,"vis":17.928,"dewpt":22.1,"snow":0,"uv":5.03372,"weather":{"icon":"c04d","code":804,"description":"Overcast clouds"},"wind_dir":94,"max_dhi":null,"clouds_hi":87,"precip":1.5625,"low_temp":23.3,"max_temp":31,"moonset_ts":1612592612,"datetime":"2021-02-06","temp":26.8,"min_temp":22.8,"clouds_mid":78,"clouds_low":10},{"moonrise_ts":1612638066,"wind_cdir":"SSE","rh":82,"pres":1007.75,"high_temp":27.5,"sunset_ts":1612697106,"ozone":248.375,"moon_phase":0.22483,"wind_gust_spd":2.9043,"snow_depth":0,"clouds":77,"ts":1612627260,"sunrise_ts":1612653788,"app_min_temp":23.5,"wind_spd":1.72706,"pop":0,"wind_cdir_full":"south-southeast","slp":1010,"moon_phase_lunation":0.84,"valid_date":"2021-02-07","app_max_temp":30,"vis":24.128,"dewpt":21.7,"snow":0,"uv":3.44152,"weather":{"icon":"c04d","code":804,"description":"Overcast clouds"},"wind_dir":161,"max_dhi":null,"clouds_hi":61,"precip":0,"low_temp":22.9,"max_temp":27.5,"moonset_ts":1612682432,"datetime":"2021-02-07","temp":25.1,"min_temp":22.8,"clouds_mid":56,"clouds_low":0},{"moonrise_ts":1612728008,"wind_cdir":"W","rh":81,"pres":1007.5,"high_temp":30.9,"sunset_ts":1612783511,"ozone":248.625,"moon_phase":0.135682,"wind_gust_spd":2.10547,"snow_depth":0,"clouds":34,"ts":1612713660,"sunrise_ts":1612740188,"app_min_temp":23.6,"wind_spd":1.73188,"pop":45,"wind_cdir_full":"west","slp":1010,"moon_phase_lunation":0.87,"valid_date":"2021-02-08","app_max_temp":33.5,"vis":15.688,"dewpt":22.3,"snow":0,"uv":6.47155,"weather":{"icon":"c02d","code":802,"description":"Scattered clouds"},"wind_dir":273,"max_dhi":null,"clouds_hi":19,"precip":2.25,"low_temp":23.4,"max_temp":30.9,"moonset_ts":1612772367,"datetime":"2021-02-08","temp":26,"min_temp":22.9,"clouds_mid":5,"clouds_low":11},{"moonrise_ts":1612817975,"wind_cdir":"S","rh":70,"pres":1007.5,"high_temp":33,"sunset_ts":1612869916,"ozone":251.625,"moon_phase":0.0672261,"wind_gust_spd":2.00195,"snow_depth":0,"clouds":64,"ts":1612800060,"sunrise_ts":1612826587,"app_min_temp":24.3,"wind_spd":1.15081,"pop":55,"wind_cdir_full":"south","slp":1010,"moon_phase_lunation":0.91,"valid_date":"2021-02-09","app_max_temp":36.2,"vis":24.128,"dewpt":21.5,"snow":0,"uv":8.48154,"weather":{"icon":"c03d","code":803,"description":"Broken clouds"},"wind_dir":185,"max_dhi":null,"clouds_hi":63,"precip":3.8125,"low_temp":23,"max_temp":33,"moonset_ts":1612862315,"datetime":"2021-02-09","temp":28.3,"min_temp":23,"clouds_mid":0,"clouds_low":28}],"city_name":"Petaling Jaya","lon":"101.60671","timezone":"Asia\/Kuala_Lumpur","lat":"3.10726","country_code":"MY","state_code":"12"}
